jsonlines/__init__.py
jsonlines/jsonlines.py
jsonlines/py.typed
jsonlines-3.1.0.dist-info/LICENSE.rst
jsonlines-3.1.0.dist-info/METADATA
jsonlines-3.1.0.dist-info/WHEEL
jsonlines-3.1.0.dist-info/top_level.txt
jsonlines-3.1.0.dist-info/RECORD
