Metadata-Version: 2.1
Name: jsonlines
Version: 3.1.0
Summary: Library with helpers for the jsonlines file format
Home-page: https://github.com/wbolster/jsonlines
Author: wouter bolsterlee
Author-email: wouter@bolsterl.ee
License: BSD
Classifier: Development Status :: 5 - Production/Stable
Classifier: Intended Audience :: Developers
Classifier: Intended Audience :: System Administrators
Classifier: License :: OSI Approved :: BSD License
Classifier: Programming Language :: Python
Classifier: Programming Language :: Python :: 3
Classifier: Programming Language :: Python :: 3 :: Only
Classifier: Topic :: Internet :: Log Analysis
Classifier: Topic :: Software Development :: Libraries :: Python Modules
Classifier: Topic :: System :: Logging
Classifier: Topic :: Utilities
Requires-Python: >=3.6
License-File: LICENSE.rst
